odoo/addons/stock_available_to_promise_release/README.rst
odoo/addons/stock_available_to_promise_release/__init__.py
odoo/addons/stock_available_to_promise_release/__manifest__.py
odoo/addons/stock_available_to_promise_release/hooks.py
odoo/addons/stock_available_to_promise_release/i18n/es.po
odoo/addons/stock_available_to_promise_release/i18n/es_AR.po
odoo/addons/stock_available_to_promise_release/i18n/fr.po
odoo/addons/stock_available_to_promise_release/i18n/hr.po
odoo/addons/stock_available_to_promise_release/i18n/it.po
odoo/addons/stock_available_to_promise_release/i18n/stock_available_to_promise_release.pot
odoo/addons/stock_available_to_promise_release/models/__init__.py
odoo/addons/stock_available_to_promise_release/models/product_product.py
odoo/addons/stock_available_to_promise_release/models/res_company.py
odoo/addons/stock_available_to_promise_release/models/res_config_settings.py
odoo/addons/stock_available_to_promise_release/models/stock_location.py
odoo/addons/stock_available_to_promise_release/models/stock_move.py
odoo/addons/stock_available_to_promise_release/models/stock_picking.py
odoo/addons/stock_available_to_promise_release/models/stock_picking_type.py
odoo/addons/stock_available_to_promise_release/models/stock_route.py
odoo/addons/stock_available_to_promise_release/models/stock_rule.py
odoo/addons/stock_available_to_promise_release/readme/CONFIGURE.md
odoo/addons/stock_available_to_promise_release/readme/CONTRIBUTORS.md
odoo/addons/stock_available_to_promise_release/readme/CREDITS.md
odoo/addons/stock_available_to_promise_release/readme/DESCRIPTION.md
odoo/addons/stock_available_to_promise_release/readme/USAGE.md
odoo/addons/stock_available_to_promise_release/security/ir.model.access.csv
odoo/addons/stock_available_to_promise_release/static/description/icon.png
odoo/addons/stock_available_to_promise_release/static/description/index.html
odoo/addons/stock_available_to_promise_release/tests/__init__.py
odoo_addon_stock_available_to_promise_release-18.0.1.6.0.2.dist-info/METADATA
odoo_addon_stock_available_to_promise_release-18.0.1.6.0.2.dist-info/WHEEL
odoo_addon_stock_available_to_promise_release-18.0.1.6.0.2.dist-info/top_level.txt
odoo_addon_stock_available_to_promise_release-18.0.1.6.0.2.dist-info/RECORD
